{
  "name": "mashling-ping-activity",
  "type": "flogo:activity",
  "ref": "github.com/TIBCOSoftware/mashling/ext/flogo/activity/ping",
  "version": "0.0.1",
  "title": "Reply (Legacy)",
  "description": "Mashling Ping Activity",
  "homepage": "https://github.com/TIBCOSoftware/mashling/tree/master/ext/flogo/activity/ping",
  "reply": true,
  "inputs":[
    {
      "name": "code",
      "type": "integer",
      "required": true
    },
    {
      "name": "data",
      "type": "any"
    }
  ],
  "outputs": [
  ]
}
